PEXE/__init__.py
PEXE/PaleEXE/__init__.py
PEXE/PaleEXE/pale_exe.py
Pale_exe-0.1.2.dist-info/METADATA
Pale_exe-0.1.2.dist-info/WHEEL
Pale_exe-0.1.2.dist-info/top_level.txt
Pale_exe-0.1.2.dist-info/RECORD
