Metadata-Version: 2.1
Name: Pale-exe
Version: 0.1.2
Requires-Python: >=3.7
Requires-Dist: maturin >=1.7.0
Provides-Extra: dev
Requires-Dist: twine >=4.0.2 ; extra == 'dev'
